logging_tz.py
logging_tz-0.1.dist-info/DESCRIPTION.rst
logging_tz-0.1.dist-info/METADATA
logging_tz-0.1.dist-info/RECORD
logging_tz-0.1.dist-info/WHEEL
logging_tz-0.1.dist-info/metadata.json
logging_tz-0.1.dist-info/top_level.txt
