Metadata-Version: 2.0
Name: logging-tz
Version: 0.1
Summary: Specify the UTC offset in Python 2 logging
Home-page: https://github.com/wimglenn/logging_tz
Author: Wim Glenn
Author-email: hey@wimglenn.com
License: MIT
Keywords: logging,datetime,timezone
Platform: UNKNOWN
Classifier: Programming Language :: Python
Classifier: Programming Language :: Python :: 2
Classifier: Programming Language :: Python :: 2 :: Only
Classifier: Topic :: System :: Logging
Classifier: Topic :: Software Development :: Libraries
Classifier: Intended Audience :: Developers
Classifier: License :: OSI Approved :: MIT License
Requires-Python: <3
Requires-Dist: pytz
Requires-Dist: tzlocal
